.gitignore
responses_validator/__init__.cpython-314-x86_64-linux-gnu.so
responses_validator/__init__.pyi
responses_validator/fields.cpython-314-x86_64-linux-gnu.so
responses_validator/fields.pyi
responses_validator/py.typed
responses_validator/schema.json
responses_validator/types.cpython-314-x86_64-linux-gnu.so
responses_validator/types.pyi
responses_validator/utils.cpython-314-x86_64-linux-gnu.so
responses_validator/utils.pyi
responses_validator-0.3.0.dist-info/METADATA
responses_validator-0.3.0.dist-info/WHEEL
responses_validator-0.3.0.dist-info/entry_points.txt
responses_validator-0.3.0.dist-info/RECORD
