Metadata-Version: 2.1
Name: responses-validator
Version: 0.3.0
Summary: Write response validation scripts for requests using flexible YAML syntax, including: status_code, headers, text, and json()
Keywords: requests,httpx,validator,validation,assertion,assert,check,matcher,testing,declarative,yaml,json,schema,jsonschema,jsonpath,api,rest,http,response,qa,automation,monitoring,utility,library
Author-Email: dongfangtianyu <7629022+dongfangtianyu@users.noreply.github.com>
Classifier: Development Status :: 4 - Beta
Classifier: Intended Audience :: Developers
Classifier: Programming Language :: Python :: 3
Classifier: Programming Language :: Python :: 3.12
Classifier: Programming Language :: Python :: 3.13
Classifier: Programming Language :: Python :: 3.14
Classifier: Topic :: Software Development :: Testing
Classifier: Topic :: Software Development :: Testing :: Acceptance
Classifier: Topic :: Software Development :: Testing :: Mocking
Classifier: Topic :: Software Development :: Libraries :: Python Modules
Classifier: Topic :: Internet :: WWW/HTTP
Classifier: Typing :: Typed
Requires-Python: >=3.12
Requires-Dist: genson~=1.2.2
Requires-Dist: jsonschema~=4.21.1
Requires-Dist: jsonpath~=0.82.2
Requires-Dist: mypy~=1.8.0
